README.rst
setup.py
pelican_ab/__init__.py
pelican_ab.egg-info/PKG-INFO
pelican_ab.egg-info/SOURCES.txt
pelican_ab.egg-info/dependency_links.txt
pelican_ab.egg-info/not-zip-safe
pelican_ab.egg-info/requires.txt
pelican_ab.egg-info/top_level.txt