Metadata-Version: 1.1
Name: pelican-ab
Version: 0.2.3
Summary: Support A/B testing for Pelican
Home-page: https://github.com/MrSenko/pelican-ab
Author: Mr. Senko
Author-email: atodorov@mrsenko.com
License: BSD
Keywords: A/B testing,Pelican
Platform: UNKNOWN
Classifier: Development Status :: 5 - Production/Stable
Classifier: Environment :: Web Environment
Classifier: Intended Audience :: Developers
Classifier: License :: OSI Approved :: BSD License
Classifier: Operating System :: OS Independent
Classifier: Programming Language :: Python
